[
  {
    "id": "679ec2fdc4a6bc423cdc77759cc226b7",
    "sport_key": "americanfootball_nfl",
    "sport_title": "NFL",
    "commence_time": "2023-10-01T13:30:00Z",
    "completed": false,
    "home_team": "Jacksonville Jaguars",
    "away_team": "Atlanta Falcons",
    "scores": null,
    "last_update": null
  },
  {
    "id": "f2a6d22204b5c05c9860c4a0934715a7",
    "sport_key": "americanfootball_nfl",
    "sport_title": "NFL",
    "commence_time": "2023-10-01T17:00:00Z",
    "completed": false,
    "home_team": "Cleveland Browns",
    "away_team": "Baltimore Ravens",
    "scores": null,
    "last_update": null
  },
  {
    "id": "c8507434f37635cdaed5f91a0fd5d54a",
    "sport_key": "americanfootball_nfl",
    "sport_title": "NFL",
    "commence_time": "2023-10-01T17:00:00Z",
    "completed": false,
    "home_team": "Buffalo Bills",
    "away_team": "Miami Dolphins",
    "scores": null,
    "last_update": null
  },
  {
    "id": "a1d0ade76d13bd11993b0e6f654ef787",
    "sport_key": "americanfootball_nfl",
    "sport_title": "NFL",
    "commence_time": "2023-10-01T17:01:00Z",
    "completed": true,
    "home_team": "Carolina Panthers",
    "away_team": "Minnesota Vikings",
    "scores": [
        {
            "name": "Carolina Panthers",
            "score": "23"
        },
        {
            "name": "Minnesota Vikings",
            "score": "21"
        }
    ],
    "last_update": null
  },
  {
    "id": "c341da353c0b5f8267f046c60e7ad2ad",
    "sport_key": "americanfootball_nfl",
    "sport_title": "NFL",
    "commence_time": "2023-10-01T17:01:00Z",
    "completed": false,
    "home_team": "Chicago Bears",
    "away_team": "Denver Broncos",
    "scores": null,
    "last_update": null
  },
  {
    "id": "21557c1796a67d11b1d49a025fc5f74f",
    "sport_key": "americanfootball_nfl",
    "sport_title": "NFL",
    "commence_time": "2023-10-01T17:01:00Z",
    "completed": false,
    "home_team": "Tennessee Titans",
    "away_team": "Cincinnati Bengals",
    "scores": null,
    "last_update": null
  },
  {
    "id": "24264c7ce10b65e575310ae99c25fb7f",
    "sport_key": "americanfootball_nfl",
    "sport_title": "NFL",
    "commence_time": "2023-10-01T17:01:00Z",
    "completed": false,
    "home_team": "Houston Texans",
    "away_team": "Pittsburgh Steelers",
    "scores": null,
    "last_update": null
  },
  {
    "id": "c5d8f1bdd3a599a9643b955f27aa1afb",
    "sport_key": "americanfootball_nfl",
    "sport_title": "NFL",
    "commence_time": "2023-10-01T17:01:00Z",
    "completed": false,
    "home_team": "Indianapolis Colts",
    "away_team": "Los Angeles Rams",
    "scores": null,
    "last_update": null
  },
  {
    "id": "99ad9bb646b822c7dc5af2f7eb2945c7",
    "sport_key": "americanfootball_nfl",
    "sport_title": "NFL",
    "commence_time": "2023-10-01T17:01:00Z",
    "completed": false,
    "home_team": "New Orleans Saints",
    "away_team": "Tampa Bay Buccaneers",
    "scores": null,
    "last_update": null
  },
  {
    "id": "bb0df615dfa27a50a742c4af2e81e9e1",
    "sport_key": "americanfootball_nfl",
    "sport_title": "NFL",
    "commence_time": "2023-10-01T17:01:00Z",
    "completed": false,
    "home_team": "Philadelphia Eagles",
    "away_team": "Washington Commanders",
    "scores": null,
    "last_update": null
  },
  {
    "id": "411f92b1c380589ce362b17fed7d2b6a",
    "sport_key": "americanfootball_nfl",
    "sport_title": "NFL",
    "commence_time": "2023-10-01T20:06:00Z",
    "completed": false,
    "home_team": "Los Angeles Chargers",
    "away_team": "Las Vegas Raiders",
    "scores": null,
    "last_update": null
  },
  {
    "id": "ea59f24a92e52fee542214baf4d33560",
    "sport_key": "americanfootball_nfl",
    "sport_title": "NFL",
    "commence_time": "2023-10-01T20:25:00Z",
    "completed": true,
    "home_team": "San Francisco 49ers",
    "away_team": "Arizona Cardinals",
    "scores": [
        {
            "name": "San Francisco 49ers",
            "score": "12"
        },
        {
            "name": "Arizona Cardinals",
            "score": "11"
        }
    ],
    "last_update": null
  },
  {
    "id": "19b8f1eaf555f3eef3ce87a61ad7ad16",
    "sport_key": "americanfootball_nfl",
    "sport_title": "NFL",
    "commence_time": "2023-10-01T20:25:00Z",
    "completed": false,
    "home_team": "Dallas Cowboys",
    "away_team": "New England Patriots",
    "scores": null,
    "last_update": null
  },
  {
    "id": "e588f3f6aef44746b18980633bd7b312",
    "sport_key": "americanfootball_nfl",
    "sport_title": "NFL",
    "commence_time": "2023-10-02T00:20:00Z",
    "completed": false,
    "home_team": "New York Jets",
    "away_team": "Kansas City Chiefs",
    "scores": null,
    "last_update": null
  },
  {
    "id": "5176634f6d30e29b08199d1e0ed6309d",
    "sport_key": "americanfootball_nfl",
    "sport_title": "NFL",
    "commence_time": "2023-10-03T00:15:00Z",
    "completed": false,
    "home_team": "New York Giants",
    "away_team": "Seattle Seahawks",
    "scores": null,
    "last_update": null
  },
  {
    "id": "115303070d36ce1e366dc4a3091c53cd",
    "sport_key": "americanfootball_nfl",
    "sport_title": "NFL",
    "commence_time": "2023-10-06T00:16:00Z",
    "completed": false,
    "home_team": "Washington Commanders",
    "away_team": "Chicago Bears",
    "scores": null,
    "last_update": null
  },
  {
    "id": "fdb93b64c39ea4a4312ffe74788b551b",
    "sport_key": "americanfootball_nfl",
    "sport_title": "NFL",
    "commence_time": "2023-10-08T13:31:00Z",
    "completed": false,
    "home_team": "Buffalo Bills",
    "away_team": "Jacksonville Jaguars",
    "scores": null,
    "last_update": null
  },
  {
    "id": "093f902b13a40cc6d60eb0a38e6d40e1",
    "sport_key": "americanfootball_nfl",
    "sport_title": "NFL",
    "commence_time": "2023-10-08T17:01:00Z",
    "completed": false,
    "home_team": "Atlanta Falcons",
    "away_team": "Houston Texans",
    "scores": null,
    "last_update": null
  },
  {
    "id": "bef2023cdadb009e088e3ef6db2ea809",
    "sport_key": "americanfootball_nfl",
    "sport_title": "NFL",
    "commence_time": "2023-10-08T17:01:00Z",
    "completed": false,
    "home_team": "Pittsburgh Steelers",
    "away_team": "Baltimore Ravens",
    "scores": null,
    "last_update": null
  },
  {
    "id": "83400c65dd84cef26b7911a49fe909f5",
    "sport_key": "americanfootball_nfl",
    "sport_title": "NFL",
    "commence_time": "2023-10-08T17:01:00Z",
    "completed": false,
    "home_team": "Detroit Lions",
    "away_team": "Carolina Panthers",
    "scores": null,
    "last_update": null
  },
  {
    "id": "b0302377625f15c445b6ce2227a50529",
    "sport_key": "americanfootball_nfl",
    "sport_title": "NFL",
    "commence_time": "2023-10-08T17:01:00Z",
    "completed": false,
    "home_team": "Indianapolis Colts",
    "away_team": "Tennessee Titans",
    "scores": null,
    "last_update": null
  },
  {
    "id": "d72ca5073fe1d69e6cd3beb37e52c081",
    "sport_key": "americanfootball_nfl",
    "sport_title": "NFL",
    "commence_time": "2023-10-08T17:01:00Z",
    "completed": false,
    "home_team": "Miami Dolphins",
    "away_team": "New York Giants",
    "scores": null,
    "last_update": null
  },
  {
    "id": "088c8fc0a2e5f02bb2591f44a41a2cd1",
    "sport_key": "americanfootball_nfl",
    "sport_title": "NFL",
    "commence_time": "2023-10-08T17:01:00Z",
    "completed": false,
    "home_team": "New England Patriots",
    "away_team": "New Orleans Saints",
    "scores": null,
    "last_update": null
  },
  {
    "id": "51324a8a97c14d19e5c8e9091ba8b37c",
    "sport_key": "americanfootball_nfl",
    "sport_title": "NFL",
    "commence_time": "2023-10-08T20:06:00Z",
    "completed": false,
    "home_team": "Arizona Cardinals",
    "away_team": "Cincinnati Bengals",
    "scores": null,
    "last_update": null
  },
  {
    "id": "483964581fdd3bb0bf48d4735c2da6e2",
    "sport_key": "americanfootball_nfl",
    "sport_title": "NFL",
    "commence_time": "2023-10-08T20:06:00Z",
    "completed": false,
    "home_team": "Los Angeles Rams",
    "away_team": "Philadelphia Eagles",
    "scores": null,
    "last_update": null
  },
  {
    "id": "8b607ae76ab2f647be17e7553ff57533",
    "sport_key": "americanfootball_nfl",
    "sport_title": "NFL",
    "commence_time": "2023-10-08T20:26:00Z",
    "completed": false,
    "home_team": "Denver Broncos",
    "away_team": "New York Jets",
    "scores": null,
    "last_update": null
  },
  {
    "id": "166bf980718e06c346f9eb8a6ed882db",
    "sport_key": "americanfootball_nfl",
    "sport_title": "NFL",
    "commence_time": "2023-10-08T20:26:00Z",
    "completed": false,
    "home_team": "Minnesota Vikings",
    "away_team": "Kansas City Chiefs",
    "scores": null,
    "last_update": null
  },
  {
    "id": "c240c9cee93e5677cdd74f93f77dd4c9",
    "sport_key": "americanfootball_nfl",
    "sport_title": "NFL",
    "commence_time": "2023-10-09T00:21:00Z",
    "completed": false,
    "home_team": "San Francisco 49ers",
    "away_team": "Dallas Cowboys",
    "scores": null,
    "last_update": null
  },
  {
    "id": "353b0556f31bd97a30c0a55212c1617f",
    "sport_key": "americanfootball_nfl",
    "sport_title": "NFL",
    "commence_time": "2023-10-10T00:16:00Z",
    "completed": false,
    "home_team": "Las Vegas Raiders",
    "away_team": "Green Bay Packers",
    "scores": null,
    "last_update": null
  }
]
